{
  "input_email_body": "Subject: Request for Updating Discord and Drupal\n\nHello customer support, I am contacting you to request an update on our Discord and Drupal integrations. My digital marketing efforts heavily depend on these platforms, and I think improving their integration will greatly enhance our tracking of performance You can reach me at liuwei@business.cn.. Given the fast-paced environment of digital marketing, it is essential that we stay at the forefront and optimize our tools to increase our reach and engagement. Could you please examine this and provide a solution that fits our requirements? If there are any additional steps I need to undertake or further details you need, please let me know My name is Maria Gonzalez.. Thank you for your time and assistance. I am looking forward to your response.",
  "list_of_masked_entities": [
    {
      "position": [
        705,
        719
      ],
      "classification": "full_name",
      "entity": "Maria Gonzalez"
    },
    {
      "position": [
        328,
        346
      ],
      "classification": "email",
      "entity": "liuwei@business.cn"
    }
  ],
  "masked_email": "Subject: Request for Updating Discord and Drupal\n\nHello customer support, I am contacting you to request an update on our Discord and Drupal integrations. My digital marketing efforts heavily depend on these platforms, and I think improving their integration will greatly enhance our tracking of performance You can reach me at [email].. Given the fast-paced environment of digital marketing, it is essential that we stay at the forefront and optimize our tools to increase our reach and engagement. Could you please examine this and provide a solution that fits our requirements? If there are any additional steps I need to undertake or further details you need, please let me know My name is [full_name].. Thank you for your time and assistance. I am looking forward to your response.",
  "category_of_the_email": "Change"
}