{
  "input_email_body": "Subject: Problem with Data Analytics\n\nThe data analytics dashboard did not update during the night because of insufficient NAS storage or possible AWS connection problems. Restarted Ansible and Zapier connections, reviewed QNAP TS-453D logs.. My contact number is +44-20-7946-0958.",
  "list_of_masked_entities": [
    {
      "position": [
        264,
        280
      ],
      "classification": "phone_number",
      "entity": "+44-20-7946-0958"
    }
  ],
  "masked_email": "Subject: Problem with Data Analytics\n\nThe data analytics dashboard did not update during the night because of insufficient NAS storage or possible AWS connection problems. Restarted Ansible and Zapier connections, reviewed QNAP TS-453D logs.. My contact number is [phone_number].",
  "category_of_the_email": "Incident"
}