{
  "input_email_body": "Subject: Technical Assistance for Network Problems\n\nFacing difficulties with network connectivity that has impacted efficiency. Restarting and updating the firmware seemed to fix the problem.. My contact number is +91-98765-43210.",
  "list_of_masked_entities": [
    {
      "position": [
        214,
        229
      ],
      "classification": "phone_number",
      "entity": "+91-98765-43210"
    }
  ],
  "masked_email": "Subject: Technical Assistance for Network Problems\n\nFacing difficulties with network connectivity that has impacted efficiency. Restarting and updating the firmware seemed to fix the problem.. My contact number is [phone_number].",
  "category_of_the_email": "Incident"
}