{
  "input_email_body": "Subject: Support Recent Engagement Decline\n\nThe engagement metrics have seen a significant drop over the past week.. My contact number is +44-20-7946-0958.",
  "list_of_masked_entities": [
    {
      "position": [
        138,
        154
      ],
      "classification": "phone_number",
      "entity": "+44-20-7946-0958"
    }
  ],
  "masked_email": "Subject: Support Recent Engagement Decline\n\nThe engagement metrics have seen a significant drop over the past week.. My contact number is [phone_number].",
  "category_of_the_email": "Incident"
}