{
  "input_email_body": "Subject: Enhancement Request for Smart-Wassermelder Integration in Existing SaaS Project Management Tools\n\nCurrently, the integration with Smart-Wassermelder is limited and does not provide a seamless user experience You can reach me at johndoe@email.com.. I would like to see additional features added to improve the overall functionality and usability of the tool. These could include automated workflows, real-time updates, and enhanced reporting capabilities. By improving the integration, users will be able to manage projects more efficiently and effectively. I believe that these enhancements would greatly benefit the tool. My name is Omar Hassan.",
  "list_of_masked_entities": [
    {
      "position": [
        643,
        654
      ],
      "classification": "full_name",
      "entity": "Omar Hassan"
    },
    {
      "position": [
        237,
        254
      ],
      "classification": "email",
      "entity": "johndoe@email.com"
    }
  ],
  "masked_email": "Subject: Enhancement Request for Smart-Wassermelder Integration in Existing SaaS Project Management Tools\n\nCurrently, the integration with Smart-Wassermelder is limited and does not provide a seamless user experience You can reach me at [email].. I would like to see additional features added to improve the overall functionality and usability of the tool. These could include automated workflows, real-time updates, and enhanced reporting capabilities. By improving the integration, users will be able to manage projects more efficiently and effectively. I believe that these enhancements would greatly benefit the tool. My name is [full_name].",
  "category_of_the_email": "Change"
}