{
  "input_email_body": "Subject: Digital Campaigns Not Performing Well and Requiring Support\n\nHello Customer Support, I am contacting you to highlight the poor performance of our digital campaigns. Even after our efforts, we are observing low engagement and unsatisfactory results. We have attempted to modify our advertising budget and refresh our content, but the results have not improved My name is Carlos Mendoza.. It seems that ineffective targeting and outdated strategies might be contributing to these issues You can reach me at maria.gonzalez@shop.es.. I would be very grateful for any advice or suggestions you can offer to enhance our campaign's effectiveness. Please let me know if you need more information from me to fully understand the situation. Thank you for your time and assistance, and I am eagerly awaiting your response.",
  "list_of_masked_entities": [
    {
      "position": [
        379,
        393
      ],
      "classification": "full_name",
      "entity": "Carlos Mendoza"
    },
    {
      "position": [
        511,
        533
      ],
      "classification": "email",
      "entity": "maria.gonzalez@shop.es"
    }
  ],
  "masked_email": "Subject: Digital Campaigns Not Performing Well and Requiring Support\n\nHello Customer Support, I am contacting you to highlight the poor performance of our digital campaigns. Even after our efforts, we are observing low engagement and unsatisfactory results. We have attempted to modify our advertising budget and refresh our content, but the results have not improved My name is [full_name].. It seems that ineffective targeting and outdated strategies might be contributing to these issues You can reach me at [email].. I would be very grateful for any advice or suggestions you can offer to enhance our campaign's effectiveness. Please let me know if you need more information from me to fully understand the situation. Thank you for your time and assistance, and I am eagerly awaiting your response.",
  "category_of_the_email": "Problem"
}