{
  "input_email_body": "Subject: Datenschutzprotokolle f\u00fcr medizinische Daten auf Seagate Expansion Desktop 6TB\n\nSehr geehrte Kundensupport, ich schreibe Ihnen um die Sicherheitsrichtlinien f\u00fcr die Speicherung medizinischer Daten auf dem Seagate Expansion Desktop 6TB zu erfragen. Da medizinische Daten sehr sensibel sind, ben\u00f6tigen sie strikte Sicherheitsma\u00dfnahmen, um Patientendaten vor unbefugtem Zugriff zu sch\u00fctzen. Ich m\u00f6chte erfahren, welche Sicherheitsprotokolle in Anwesenheit vorhanden sind, um die sichere Speicherung medizinischer Daten auf diesem Ger\u00e4t zu gew\u00e4hrleisten You can reach me at sophia.rossi@service.it.. Gibt es Verfahren zur Verschl\u00fcsselung? Sind Zugriffssteuerungen oder Authentifizierungsmethoden vorhanden? Gibt es eine Einhaltung von regulatorischen Standards wie HIPAA? Dar\u00fcber hinaus w\u00fcrde ich wissen, ob es Empfehlungen f\u00fcr die sichere L\u00f6schung von Daten gibt, wenn das Ger\u00e4t nicht mehr ben\u00f6tigt wird? Ich freue mich auf Ihre R\u00fcckmeldung mit weiteren Informationen \u00fcber die Sicherheitsrichtlinien f\u00fcr die medizinische Daten Speicherung auf dem Seagate Expansion Desktop 6TB. My name is Fatima Al-Farsi.",
  "list_of_masked_entities": [
    {
      "position": [
        1095,
        1104
      ],
      "classification": "full_name",
      "entity": "Fatima Al"
    },
    {
      "position": [
        579,
        602
      ],
      "classification": "email",
      "entity": "sophia.rossi@service.it"
    }
  ],
  "masked_email": "Subject: Datenschutzprotokolle f\u00fcr medizinische Daten auf Seagate Expansion Desktop 6TB\n\nSehr geehrte Kundensupport, ich schreibe Ihnen um die Sicherheitsrichtlinien f\u00fcr die Speicherung medizinischer Daten auf dem Seagate Expansion Desktop 6TB zu erfragen. Da medizinische Daten sehr sensibel sind, ben\u00f6tigen sie strikte Sicherheitsma\u00dfnahmen, um Patientendaten vor unbefugtem Zugriff zu sch\u00fctzen. Ich m\u00f6chte erfahren, welche Sicherheitsprotokolle in Anwesenheit vorhanden sind, um die sichere Speicherung medizinischer Daten auf diesem Ger\u00e4t zu gew\u00e4hrleisten You can reach me at [email].. Gibt es Verfahren zur Verschl\u00fcsselung? Sind Zugriffssteuerungen oder Authentifizierungsmethoden vorhanden? Gibt es eine Einhaltung von regulatorischen Standards wie HIPAA? Dar\u00fcber hinaus w\u00fcrde ich wissen, ob es Empfehlungen f\u00fcr die sichere L\u00f6schung von Daten gibt, wenn das Ger\u00e4t nicht mehr ben\u00f6tigt wird? Ich freue mich auf Ihre R\u00fcckmeldung mit weiteren Informationen \u00fcber die Sicherheitsrichtlinien f\u00fcr die medizinische Daten Speicherung auf dem Seagate Expansion Desktop 6TB. My name is [full_name]-Farsi.",
  "category_of_the_email": "Request"
}