{
  "input_email_body": "Subject: Anforderungen f\u00fcr Terraform-Integration in Ihrem Projektmanagement-SaaS\n\nSehr geehrte Kundensupport, ich wende mich an Sie, um die Systemanforderungen f\u00fcr die Integration von Terraform in Ihr Projektmanagement-SaaS zu kl\u00e4ren My name is Carlos Mendoza.. Insbesondere m\u00f6chte ich gerne wissen, welche Betriebssysteme und Softwareversionen unterst\u00fctzt werden. Gibt es spezielle Abh\u00e4ngigkeiten oder Bibliotheken, die installiert werden m\u00fcssen? Ich w\u00fcrde mich auch \u00fcber Informationen zu m\u00f6glichen Kompatibilit\u00e4tsproblemen freuen, die ich vorhersehen sollte. Zus\u00e4tzlich w\u00fcrde ich gerne Ratschl\u00e4ge zum Aufkl\u00e4ren von h\u00e4ufig auftretenden Problemen erhalten, die w\u00e4hrend der Integrationsphase auftreten k\u00f6nnen You can reach me at david.kim@corp.kr.. Ich freue mich auf die potenziellen Vorteile der Verwendung von Terraform mit Ihrem SaaS, aber ich m\u00f6chte sicherstellen, dass ich einen glatt und erfolgreichen Integrationsprozess habe. Vielen Dank f\u00fcr Ihre Zeit und Unterst\u00fctzung. Ich freue mich darauf, bald von Ihnen zu h\u00f6ren. Bitte geben Sie mir Bescheid, falls Sie zus\u00e4tzliche Informationen von mir ben\u00f6tigen, um meine Anfrage besser zu beantworten. Ich habe die Dokumentation bereits gepr\u00fcft, aber ich w\u00fcrde gerne detailliertere Informationen zu den Systemanforderungen haben.",
  "list_of_masked_entities": [
    {
      "position": [
        245,
        259
      ],
      "classification": "full_name",
      "entity": "Carlos Mendoza"
    },
    {
      "position": [
        725,
        742
      ],
      "classification": "email",
      "entity": "david.kim@corp.kr"
    }
  ],
  "masked_email": "Subject: Anforderungen f\u00fcr Terraform-Integration in Ihrem Projektmanagement-SaaS\n\nSehr geehrte Kundensupport, ich wende mich an Sie, um die Systemanforderungen f\u00fcr die Integration von Terraform in Ihr Projektmanagement-SaaS zu kl\u00e4ren My name is [full_name].. Insbesondere m\u00f6chte ich gerne wissen, welche Betriebssysteme und Softwareversionen unterst\u00fctzt werden. Gibt es spezielle Abh\u00e4ngigkeiten oder Bibliotheken, die installiert werden m\u00fcssen? Ich w\u00fcrde mich auch \u00fcber Informationen zu m\u00f6glichen Kompatibilit\u00e4tsproblemen freuen, die ich vorhersehen sollte. Zus\u00e4tzlich w\u00fcrde ich gerne Ratschl\u00e4ge zum Aufkl\u00e4ren von h\u00e4ufig auftretenden Problemen erhalten, die w\u00e4hrend der Integrationsphase auftreten k\u00f6nnen You can reach me at [email].. Ich freue mich auf die potenziellen Vorteile der Verwendung von Terraform mit Ihrem SaaS, aber ich m\u00f6chte sicherstellen, dass ich einen glatt und erfolgreichen Integrationsprozess habe. Vielen Dank f\u00fcr Ihre Zeit und Unterst\u00fctzung. Ich freue mich darauf, bald von Ihnen zu h\u00f6ren. Bitte geben Sie mir Bescheid, falls Sie zus\u00e4tzliche Informationen von mir ben\u00f6tigen, um meine Anfrage besser zu beantworten. Ich habe die Dokumentation bereits gepr\u00fcft, aber ich w\u00fcrde gerne detailliertere Informationen zu den Systemanforderungen haben.",
  "category_of_the_email": "Request"
}